compromise_marian/__init__.py
compromise_marian/configuration.py
compromise_marian/dataloader.py
compromise_marian/model.py
compromise_marian/pl_wrapper.py
compromise_marian-0.1.2.dist-info/METADATA
compromise_marian-0.1.2.dist-info/WHEEL
compromise_marian-0.1.2.dist-info/top_level.txt
compromise_marian-0.1.2.dist-info/RECORD
