Metadata-Version: 2.1
Name: compromise-marian
Version: 0.1.2
Summary: Marian model but with two decoders
Author: Le Minh Khoi
License: MIT
Classifier: Programming Language :: Python :: 3
Classifier: License :: OSI Approved :: MIT License
Classifier: Operating System :: OS Independent
Requires-Python: >=3.8
Requires-Dist: torch
Requires-Dist: pytorch-lightning
Requires-Dist: wandb
Requires-Dist: transformers
Requires-Dist: datasets
Requires-Dist: tokenizers
Requires-Dist: evaluate
Requires-Dist: sacrebleu
Requires-Dist: sentencepiece
Requires-Dist: sacremoses
